nonebot_plugin_brecreport/__init__.py
nonebot_plugin_brecreport/config.py
nonebot_plugin_brecreport-0.1.5.dist-info/LICENSE
nonebot_plugin_brecreport-0.1.5.dist-info/METADATA
nonebot_plugin_brecreport-0.1.5.dist-info/WHEEL
nonebot_plugin_brecreport-0.1.5.dist-info/RECORD
