Metadata-Version: 2.1
Name: nonebot-plugin-brecreport
Version: 0.1.5
Summary: 该插件提供了一个位于 /brec_report 的路由，并和录播姬适配，实现实现几乎实时的开播提醒 (需要安装录播姬)
Home-page: https://github.com/A-nemon-e/nonebot-plugin-brecreport
License: AGPL-3.0
Author: Anec
Author-email: a-nemon-e@outlook.com
Requires-Python: >=3.8,<4.0
Classifier: License :: OSI Approved :: GNU Affero General Public License v3
Classifier: Programming Language :: Python :: 3
Classifier: Programming Language :: Python :: 3.8
Classifier: Programming Language :: Python :: 3.9
Classifier: Programming Language :: Python :: 3.10
Classifier: Programming Language :: Python :: 3.11
Classifier: Programming Language :: Python :: 3.12
Requires-Dist: nonebot2[fastapi] (>=2.0.1,<3.0.0)
Requires-Dist: pydantic (>=1.10.0,<2.0.0)
